shapes/__init__.py
shapes/circled.py
shapes/cylindered.py
shapes/ellipsed.py
shapes/ellipsoid.py
shapes/rectangled.py
shapes/sphered.py
shapes/spheroid.py
shapes/squared.py
shapes/triangled.py
GeometricShapes-0.1.5.dist-info/LICENSE
GeometricShapes-0.1.5.dist-info/METADATA
GeometricShapes-0.1.5.dist-info/WHEEL
GeometricShapes-0.1.5.dist-info/top_level.txt
GeometricShapes-0.1.5.dist-info/RECORD
