Metadata-Version: 2.1
Name: GeometricShapes
Version: 0.1.5
Summary: Making calculations of geometric shapes easier
Home-page: https://github.com/Bikram-ghuku/shapes
Author: BikramGhuku
License: MIT
Platform: UNKNOWN
License-File: LICENSE
Requires-Dist: scipy (==1.10.0)
